{
    "step":  "CONTENT_ENGINE_GLOBAL_MANUAL_BRAIN_DASHBOARD_INTERFACE_RECONCILIATION_FINAL_APPROVAL_REVIEW",
    "component":  "GLOBAL_MANUAL_BRAIN_DASHBOARD_INTERFACE_RECONCILIATION",
    "phase":  "FINAL_APPROVAL_REVIEW",
    "status":  "FINAL_APPROVAL_REVIEWED",
    "classification":  "RECONCILIATION_DESIGN_APPROVED_FOR_IMPLEMENTATION_PLAN_ONLY",
    "generated_at_utc":  "2026-06-20T07:49:52.2729965Z",
    "consumed":  {
                     "review_report":  "00_SYSTEM/content_engine/reports/GLOBAL_MANUAL_BRAIN_DASHBOARD_INTERFACE_RECONCILIATION_REVIEW_HARDENING_REPORT.json",
                     "review_manifest":  "00_SYSTEM/content_engine/manifests/GLOBAL_MANUAL_BRAIN_DASHBOARD_INTERFACE_RECONCILIATION_REVIEW_HARDENING_MANIFEST.json",
                     "review_seal":  "00_SYSTEM/content_engine/manifests/GLOBAL_MANUAL_BRAIN_DASHBOARD_INTERFACE_RECONCILIATION_REVIEW_HARDENING_SEAL.json",
                     "review_summary":  "05_REPORTS/content_engine/GLOBAL_MANUAL_BRAIN_DASHBOARD_INTERFACE_RECONCILIATION_REVIEW_HARDENING_SUMMARY.md",
                     "review_report_sha256":  "287a83e03a416c2226f37a4ecbd767a53deb39d54848e2642b2ae2e770543f08",
                     "review_manifest_sha256":  "3ec6315b19607b8ed5db5be4c7a2cf31967f29d54126d8ee86aa14254bc72394",
                     "review_summary_sha256":  "27565bb59b66310b8ec9f916468e7e3a84a7d27b126ab4c693e49067be50551a"
                 },
    "approval_decision":  {
                              "approved":  true,
                              "approved_for":  "IMPLEMENTATION_PLAN_ONLY",
                              "not_approved_for":  [
                                                       "source_file_write",
                                                       "test_file_write",
                                                       "automatic_block_build",
                                                       "runtime_execution",
                                                       "dashboard_runtime_execution",
                                                       "interface_runtime_execution",
                                                       "manual_mutation",
                                                       "brain_mutation",
                                                       "ARGOS_mutation",
                                                       "queue_mutation",
                                                       "publication_mutation",
                                                       "automation_trigger",
                                                       "publishing",
                                                       "scheduling"
                                                   ],
                              "reason":  "Review hardening validates truth object contract, evidence hierarchy, layer boundaries, dashboard visualization gate, interface/HUD gate, capability and risk hardening. It is sufficient only to plan implementation, not to build or execute."
                          },
    "approved_design_scope":  {
                                  "future_implementation_plan_must_define":  [
                                                                                 "source_allowlist",
                                                                                 "test_allowlist",
                                                                                 "truth_object_artifact_contract",
                                                                                 "manual_truth_matrix_contract",
                                                                                 "brain_truth_matrix_contract",
                                                                                 "dashboard_truth_matrix_contract",
                                                                                 "interface_hud_truth_matrix_contract",
                                                                                 "conflict_matrix_contract",
                                                                                 "capability_matrix_contract",
                                                                                 "risk_matrix_contract",
                                                                                 "protected_roots_no_touch_policy",
                                                                                 "productive_operations_block_policy",
                                                                                 "runtime_block_policy",
                                                                                 "build_acceptance_gates",
                                                                                 "post_build_audit_gates",
                                                                                 "gate_close_validation_gates"
                                                                             ],
                                  "implementation_plan_must_not_define":  [
                                                                              "productive_enablement",
                                                                              "publishing_enablement",
                                                                              "queue_write_enablement",
                                                                              "automation_trigger_enablement",
                                                                              "manual_mutation_enablement",
                                                                              "brain_mutation_enablement",
                                                                              "ARGOS_mutation_enablement"
                                                                          ]
                              },
    "approval_gates":  {
                           "repo_precheck_clean_synced":  true,
                           "review_hardening_consumed":  true,
                           "review_hashes_validated":  true,
                           "review_required_sections_present":  true,
                           "truth_object_contract_approved_for_planning":  true,
                           "evidence_hierarchy_approved_for_planning":  true,
                           "dashboard_visualization_gate_approved_for_planning":  true,
                           "interface_hud_gate_approved_for_planning":  true,
                           "capability_risk_hardening_approved_for_planning":  true,
                           "source_files_written":  false,
                           "test_files_written":  false,
                           "build_performed":  false,
                           "runtime_performed":  false,
                           "productive_operations_blocked":  true,
                           "manual_mutation_blocked":  true,
                           "brain_mutation_blocked":  true,
                           "dashboard_runtime_mutation_blocked":  true,
                           "interface_runtime_mutation_blocked":  true,
                           "argos_mutation_blocked":  true,
                           "queue_publication_automation_blocked":  true
                       },
    "next_safe_step":  "CONTENT_ENGINE_GLOBAL_MANUAL_BRAIN_DASHBOARD_INTERFACE_RECONCILIATION_IMPLEMENTATION_PLAN"
}
