{
  "binary_checks": "DEFINED",
  "block": "BLOQUE_3_SOURCE_RESOLVER_INTEGRITY_GUARD",
  "block_4_allowed_now": false,
  "brain_write_allowed_now": false,
  "capa9_allowed_now": false,
  "encoding_checks": "DEFINED",
  "execution_allowed_now": false,
  "fixture_based_validation": true,
  "freshness_checks": "DEFINED",
  "hash_checks": "DEFINED",
  "lifecycle_status": "BUILT_PENDING_POST_AUDIT",
  "manual_write_allowed_now": false,
  "mtime_checks": "DEFINED",
  "n8n_allowed_now": false,
  "next_safe_step": "BLOQUE_3_POST_BUILD_AUDIT",
  "no_brain_read": true,
  "no_manual_current_read": true,
  "no_reports_brain_read": true,
  "publishing_allowed_now": false,
  "real_source_read_performed": false,
  "report_id": "BRIDGE_BLOCK_3_SOURCE_INTEGRITY_REPORT",
  "reports_brain_write_allowed_now": false,
  "size_checks": "DEFINED",
  "status": "PASS",
  "toctou_checks": "DEFINED",
  "webhook_allowed_now": false
}
